hashid.py
hashID-3.1.4.dist-info/DESCRIPTION.rst
hashID-3.1.4.dist-info/entry_points.txt
hashID-3.1.4.dist-info/METADATA
hashID-3.1.4.dist-info/metadata.json
hashID-3.1.4.dist-info/RECORD
hashID-3.1.4.dist-info/top_level.txt
hashID-3.1.4.dist-info/WHEEL
