Metadata-Version: 1.1
Name: hashID
Version: 3.1.4
Summary: Software to identify the different types of hashes
Home-page: https://github.com/psypanda/hashID
Author: c0re
Author-email: c0re@psypanda.org
License: GNU GPL
Download-URL: https://github.com/psypanda/hashID/tarball/v3.1.4
Keywords: hashid hash identifier hash-identifier
Platform: UNKNOWN
Classifier: Development Status :: 5 - Production/Stable
Classifier: Environment :: Console
Classifier: Natural Language :: English
Classifier: Intended Audience :: Other Audience
Classifier: License :: OSI Approved :: GNU General Public License v3 or later (GPLv3+)
Classifier: Operating System :: OS Independent
Classifier: Programming Language :: Python :: 2.7
Classifier: Programming Language :: Python :: 3
Classifier: Programming Language :: Python :: 3.3
Classifier: Programming Language :: Python :: 3.4
